setup.cfg
setup.py
fennec/__init__.py
fennec/workspace.py
fennec.egg-info/PKG-INFO
fennec.egg-info/SOURCES.txt
fennec.egg-info/dependency_links.txt
fennec.egg-info/requires.txt
fennec.egg-info/top_level.txt
fennec/testing/__init__.py
fennec/testing/almost.py
fennec/utils/__init__.py
fennec/utils/array.py
fennec/utils/index.py
tests/__init__.py
tests/test_workspace.py
tests/test_utils/__init__.py
tests/test_utils/test_array.py
tests/test_utils/test_index.py