Metadata-Version: 1.1
Name: fennec
Version: 0.0.2
Summary: Fennec is a simple toolbox for statistical analysis.
Home-page: https://github.com/amaotone/fennec
Author: Amane SUZUKI
Author-email: amane.suzu@gmail.com
License: MIT
Platform: UNKNOWN
Classifier: Development Status :: 3 - Alpha
Classifier: License :: OSI Approved :: MIT License
Classifier: Programming Language :: Python
Classifier: Programming Language :: Python :: 3.4
Classifier: Programming Language :: Python :: 3.5
Classifier: Programming Language :: Python :: 3 :: Only
Classifier: Topic :: Scientific/Engineering
